{
  "2025-2-24": [
    [
      "2025-02-24 11:33AM",
      "Penn schools scrubbed their DEI websites. Here\u2019s what\u2019s left."
    ],
    [
      "2025-02-24 12:05PM",
      "Photo Gallery | Philadelphia Eagles Super Bowl LIX Victory Parade"
    ]
  ],
  "2025-2-25": [
    [
      "2025-02-25 03:30AM",
      "Photo Gallery | Philadelphia Eagles Super Bowl LIX Victory Parade"
    ],
    [
      "2025-02-25 03:25PM",
      "Weekend of Basketball Recap"
    ]
  ],
  "2025-2-26": [
    [
      "2025-02-26 03:30AM",
      "Weekend of Basketball Recap"
    ]
  ],
  "2025-2-27": [
    [
      "2025-02-27 03:29AM",
      "Penn(y) For Your Thoughts - Episode 3"
    ],
    [
      "2025-02-27 03:25PM",
      "In Photos: Revisiting the protests, movements, and community that helped shape Black history at Penn"
    ]
  ],
  "2025-2-28": [
    [
      "2025-02-28 03:29AM",
      "In Photos: Revisiting the protests, movements, and community that helped shape Black history at Penn"
    ]
  ],
  "2025-3-1": [
    [
      "2025-03-01 03:27AM",
      "In Photos: Revisiting the protests, movements, and community that helped shape Black history at Penn"
    ]
  ],
  "2025-3-2": [
    [
      "2025-03-02 03:26AM",
      "In Photos: Revisiting the protests, movements, and community that helped shape Black history at Penn"
    ]
  ],
  "2025-3-3": [
    [
      "2025-03-03 03:31AM",
      "This Week in Photos: Feb. 24\u2013March 2"
    ]
  ],
  "2025-3-4": [
    [
      "2025-03-04 03:28AM",
      "This Week in Photos: Feb. 24\u2013March 2"
    ]
  ],
  "2025-3-5": [
    [
      "2025-03-05 03:31AM",
      "This Week in Photos: Feb. 24\u2013March 2"
    ]
  ],
  "2025-3-6": [
    [
      "2025-03-06 03:30AM",
      "This Week in Photos: Feb. 24\u2013March 2"
    ]
  ],
  "2025-3-7": [
    [
      "2025-03-07 03:30AM",
      "This Week in Photos: Feb. 24\u2013March 2"
    ]
  ],
  "2025-3-8": [
    [
      "2025-03-08 03:23AM",
      "This Week in Photos: Feb. 24\u2013March 2"
    ],
    [
      "2025-03-08 03:18PM",
      "Penn students react to test-mandatory admissions policy for 2025-26 cycle"
    ]
  ],
  "2025-3-9": [
    [
      "2025-03-09 04:23AM",
      "Penn students react to test-mandatory admissions policy for 2025-26 cycle"
    ]
  ],
  "2025-3-10": [
    [
      "2025-03-10 04:26AM",
      "Penn students react to test-mandatory admissions policy for 2025-26 cycle"
    ]
  ],
  "2025-3-11": [
    [
      "2025-03-11 04:30AM",
      "Penn students react to test-mandatory admissions policy for 2025-26 cycle"
    ]
  ],
  "2025-3-12": [
    [
      "2025-03-12 04:32AM",
      "Penn students react to test-mandatory admissions policy for 2025-26 cycle"
    ]
  ],
  "2025-3-13": [
    [
      "2025-03-13 04:31AM",
      "Penn students react to test-mandatory admissions policy for 2025-26 cycle"
    ]
  ],
  "2025-3-14": [
    [
      "2025-03-14 04:29AM",
      "Penn students react to test-mandatory admissions policy for 2025-26 cycle"
    ]
  ],
  "2025-3-15": [
    [
      "2025-03-15 04:28AM",
      "Penn students react to test-mandatory admissions policy for 2025-26 cycle"
    ]
  ],
  "2025-3-16": [
    [
      "2025-03-16 04:27AM",
      "Penn students react to test-mandatory admissions policy for 2025-26 cycle"
    ]
  ]
}